earlyster_probability/__init__.py
earlyster_probability/binomial_distribution.py
earlyster_probability/gaussian_distribution.py
earlyster_probability/general_distribution.py
earlyster_probability-0.1.1.dist-info/LICENSE
earlyster_probability-0.1.1.dist-info/METADATA
earlyster_probability-0.1.1.dist-info/WHEEL
earlyster_probability-0.1.1.dist-info/top_level.txt
earlyster_probability-0.1.1.dist-info/RECORD
