Metadata-Version: 2.1
Name: earlyster-probability
Version: 0.1.1
Summary: A Binomial and Gaussian Distribution Probability Library
Home-page: https://github.com/earlyster/earlyster_probability
Author: Justin Early
Author-email: earlyster@gmail.com
License: MIT
Platform: UNKNOWN
Classifier: Development Status :: 2 - Pre-Alpha
Classifier: License :: OSI Approved :: MIT License
Classifier: Programming Language :: Python
Classifier: Programming Language :: Python :: 3.7
